wonderbits/MyCore.py
wonderbits/MySerial.py
wonderbits/MyUtil.py
wonderbits/Tool.py
wonderbits/WBAcceleration.py
wonderbits/WBAudioPlayer.py
wonderbits/WBBuggy.py
wonderbits/WBClimate.py
wonderbits/WBControl.py
wonderbits/WBDisplay.py
wonderbits/WBDisplaymini.py
wonderbits/WBDistance.py
wonderbits/WBDriver.py
wonderbits/WBError.py
wonderbits/WBFingerprint.py
wonderbits/WBHall.py
wonderbits/WBIoExtension.py
wonderbits/WBLed.py
wonderbits/WBLedMatrix.py
wonderbits/WBLedTape.py
wonderbits/WBLight.py
wonderbits/WBLightBelt.py
wonderbits/WBMakeyMakey.py
wonderbits/WBMultimeter.py
wonderbits/WBNebulier.py
wonderbits/WBNfc.py
wonderbits/WBObserver.py
wonderbits/WBPi.py
wonderbits/WBPressure.py
wonderbits/WBPressurePad.py
wonderbits/WBPulse.py
wonderbits/WBRfCommunication.py
wonderbits/WBRfTelecontroller.py
wonderbits/WBRtc.py
wonderbits/WBSignal.py
wonderbits/WBSlider.py
wonderbits/WBTransmitter.py
wonderbits/WBUltrasonic.py
wonderbits/WBUpload.py
wonderbits/WBVoice.py
wonderbits/WBWonder.py
wonderbits/WBits.py
wonderbits/__init__.py
wonderbits/__version__.py
wonderbits/cli.py
wonderbits/core.py
wonderbits/event.py
wonderbits/event_handle.py
wonderbits/public.py
wonderbits-6.1.4.dist-info/LICENSE
wonderbits-6.1.4.dist-info/METADATA
wonderbits-6.1.4.dist-info/WHEEL
wonderbits-6.1.4.dist-info/entry_points.txt
wonderbits-6.1.4.dist-info/top_level.txt
wonderbits-6.1.4.dist-info/RECORD
