Metadata-Version: 2.1
Name: wonderbits
Version: 6.1.4
Summary: wonderbits by mfeducation.
Home-page: https://github.com/BigCircleLaw/wonderguy.git
Author: mfe
Author-email: 794557226@qq.com
License: MIT
Platform: UNKNOWN
Classifier: License :: OSI Approved :: MIT License
Classifier: Operating System :: OS Independent
Classifier: Programming Language :: Python :: 3
Requires-Python: >=3.0.0
Requires-Dist: requests
Requires-Dist: pyserial
Requires-Dist: Click
Requires-Dist: wonderbits-ampy (>=1.1.5)
Requires-Dist: esptool
Requires-Dist: wonderbitscloud (>=1.0.0)
